sphinx_subfigure/__init__.py
sphinx_subfigure/_compat.py
sphinx_subfigure/main.py
sphinx_subfigure/tr_html.py
sphinx_subfigure/tr_latex.py
sphinx_subfigure-0.2.4.dist-info/LICENSE
sphinx_subfigure-0.2.4.dist-info/WHEEL
sphinx_subfigure-0.2.4.dist-info/METADATA
sphinx_subfigure-0.2.4.dist-info/RECORD
