Metadata-Version: 2.1
Name: sphinx_subfigure
Version: 0.2.4
Summary: A sphinx extension to create sub-figures.
Keywords: sphinx,subfigure
Author-email: Chris Sewell <chrisj_sewell@hotmail.com>
Requires-Python: >=3.7
Classifier: Development Status :: 4 - Beta
Classifier: License :: OSI Approved :: MIT License
Classifier: Programming Language :: Python :: 3
Classifier: Topic :: Software Development :: Libraries :: Python Modules
Classifier: Topic :: Text Processing :: Markup
Classifier: Framework :: Sphinx :: Extension
Requires-Dist: sphinx
Requires-Dist: myst-parser ; extra == "docs"
Requires-Dist: furo ; extra == "docs"
Requires-Dist: pytest ; extra == "testing"
Requires-Dist: pytest-cov ; extra == "testing"
Requires-Dist: pytest-regressions ; extra == "testing"
Requires-Dist: pytest-param-files ; extra == "testing"
Requires-Dist: sphinx-pytest>=0.0.4 ; extra == "testing"
Requires-Dist: beautifulsoup4 ; extra == "testing"
Project-URL: Homepage, https://github.com/chrisjsewell/sphinx-subfigure
Provides-Extra: docs
Provides-Extra: testing
